odoo8_addon_l10n_it_invoices_data_communication_fatturapa-8.0.1.0.0.99.dev5-nspkg.pth
odoo_addons/l10n_it_invoices_data_communication_fatturapa/README.rst
odoo_addons/l10n_it_invoices_data_communication_fatturapa/__init__.py
odoo_addons/l10n_it_invoices_data_communication_fatturapa/__openerp__.py
odoo_addons/l10n_it_invoices_data_communication_fatturapa/i18n/l10n_it_invoices_data_communication_fatturapa.pot
odoo_addons/l10n_it_invoices_data_communication_fatturapa/models/__init__.py
odoo_addons/l10n_it_invoices_data_communication_fatturapa/models/communication.py
odoo_addons/l10n_it_invoices_data_communication_fatturapa/readme/CONTRIBUTORS.rst
odoo_addons/l10n_it_invoices_data_communication_fatturapa/readme/DESCRIPTION.rst
odoo_addons/l10n_it_invoices_data_communication_fatturapa/static/description/icon.png
odoo_addons/l10n_it_invoices_data_communication_fatturapa/static/description/index.html
odoo_addons/l10n_it_invoices_data_communication_fatturapa/views/communication_view.xml
odoo8_addon_l10n_it_invoices_data_communication_fatturapa-8.0.1.0.0.99.dev5.dist-info/METADATA
odoo8_addon_l10n_it_invoices_data_communication_fatturapa-8.0.1.0.0.99.dev5.dist-info/WHEEL
odoo8_addon_l10n_it_invoices_data_communication_fatturapa-8.0.1.0.0.99.dev5.dist-info/namespace_packages.txt
odoo8_addon_l10n_it_invoices_data_communication_fatturapa-8.0.1.0.0.99.dev5.dist-info/top_level.txt
odoo8_addon_l10n_it_invoices_data_communication_fatturapa-8.0.1.0.0.99.dev5.dist-info/RECORD
