Metadata-Version: 2.1
Name: odoo8-addon-l10n-it-invoices-data-communication-fatturapa
Version: 8.0.1.0.0.99.dev5
Summary: Integrazione fatturazione elettronica e Comunicazione dati fatture (c.d. "nuovo spesometro")
Home-page: https://github.com/OCA/l10n-italy/tree/8.0/l10n_it_invoices_data_communication_fatturapa
Author: Agile Business Group, Odoo Community Association (OCA)
Author-email: support@odoo-community.org
License: LGPL-3
Platform: UNKNOWN
Classifier: Programming Language :: Python
Classifier: Framework :: Odoo
Classifier: License :: OSI Approved :: GNU Lesser General Public License v3 (LGPLv3)
Requires-Python: ~=2.7
Requires-Dist: odoo8-addon-l10n-it-fatturapa-in
Requires-Dist: odoo8-addon-l10n-it-fatturapa-out
Requires-Dist: odoo8-addon-l10n-it-invoices-data-communication
Requires-Dist: odoo (<9.0a,>=8.0a)
